freedb/__init__.py
freedb/admin.py
freedb/apps.py
freedb/database.py
freedb/models.py
freedb/serializers.py
freedb/tests.py
freedb/urls.py
freedb/views.py
freedb/management/__init__.py
freedb/management/commands/__init__.py
freedb/management/commands/initadmin.py
freedb/migrations/0001_initial.py
freedb/migrations/__init__.py
freedb_site/__init__.py
freedb_site/settings.py
freedb_site/urls.py
freedb_site/wsgi.py
freedb_site/staticfiles/css/bootstrap-grid.css
freedb_site/staticfiles/css/bootstrap-grid.css.map
freedb_site/staticfiles/css/bootstrap-grid.min.css
freedb_site/staticfiles/css/bootstrap-grid.min.css.map
freedb_site/staticfiles/css/bootstrap-reboot.css
freedb_site/staticfiles/css/bootstrap-reboot.css.map
freedb_site/staticfiles/css/bootstrap-reboot.min.css
freedb_site/staticfiles/css/bootstrap-reboot.min.css.map
freedb_site/staticfiles/css/bootstrap.css
freedb_site/staticfiles/css/bootstrap.css.map
freedb_site/staticfiles/css/bootstrap.min.css
freedb_site/staticfiles/css/bootstrap.min.css.map
freedb_site/staticfiles/frontend/main.js
freedb_site/staticfiles/js/bootstrap.bundle.js
freedb_site/staticfiles/js/bootstrap.bundle.js.map
freedb_site/staticfiles/js/bootstrap.bundle.min.js
freedb_site/staticfiles/js/bootstrap.bundle.min.js.map
freedb_site/staticfiles/js/bootstrap.js
freedb_site/staticfiles/js/bootstrap.js.map
freedb_site/staticfiles/js/bootstrap.min.js
freedb_site/staticfiles/js/bootstrap.min.js.map
freedb_site/staticfiles/js/jquery-3.5.1.min.js
frontend/__init__.py
frontend/admin.py
frontend/apps.py
frontend/models.py
frontend/tests.py
frontend/urls.py
frontend/views.py
frontend/migrations/__init__.py
frontend/static/frontend/main.js
frontend/templates/frontend/index.html
freedb-0.0.3.dist-info/METADATA
freedb-0.0.3.dist-info/WHEEL
freedb-0.0.3.dist-info/top_level.txt
freedb-0.0.3.dist-info/RECORD
