Metadata-Version: 2.1
Name: freedb
Version: 0.0.3
Summary: UNKNOWN
Home-page: UNKNOWN
Author: UNKNOWN
Author-email: UNKNOWN
License: UNKNOWN
Platform: UNKNOWN
Requires-Dist: django
Requires-Dist: pymongo
Requires-Dist: djangorestframework
Requires-Dist: django-cors-headers
